Workbook

Sheet Summary
B2: ZEPTO (KIRANAKART TECHNOLOGIES LTD)
B3: 3-Statement Financial Model & DCF Valuation — Portfolio / Interview Project
B5: Company snapshot
B6: Sector | C6: Quick-commerce (10-minute grocery delivery), India
B7: Founded | C7: 2021 (as Kiranakart Technologies Pvt Ltd; rebranded Zepto, April 2025)
B8: Status modeled | C8: IPO-bound — updated DRHP filed with SEBI, June 2026 (₹8,010 Cr fresh issue + OFS)
B9: Last private round | C9: ~$7.0bn valuation, October 2025
B10: IPO price band (reported) | C10: ~$5.6bn - $5.95bn implied valuation
B12: Historical financials (₹ Crore, actual per DRHP)
C13: FY25A | D13: FY26A | E13: CAGR (FY23-26)
B14: Revenue | C14: ='Income Statement'!D6 -> 11110 | D14: ='Income Statement'!E6 -> 22624 | E14: =('Income Statement'!E6/'Income Statement'!B6)^(1/3)-1 -> 1.2355349
B15: Net income / (loss) | C15: ='Income Statement'!D27 -> -4700.01 | D15: ='Income Statement'!E27 -> -5905.0384
B17: DCF valuation output (base case)
B18: WACC | C18: =Assumptions!B36 -> 0.15110885
B19: Terminal growth rate | C19: =Assumptions!B37 -> 0.05
B20: Enterprise Value (₹ Cr) | C20: =DCF!B25 -> 19678.446
B21: Equity Value (₹ Cr) | C21: =DCF!B27 -> 20678.446
B22: Equity Value (US$ bn) | C22: =DCF!B28 -> 2.363251
B23: Implied premium/(discount) vs. last private round | C23: =DCF!B31 -> -0.66239271
B24: Implied premium/(discount) vs. IPO band midpoint | C24: =DCF!B32 -> -0.59077905
B26: How to use this workbook
B27: 1. Assumptions — every driver of the model (growth, margins, working capital, WACC, terminal growth). Blue = hardcoded input; edit these to stress-test the model.
B28: 2. Income Statement — fully formula-linked to Assumptions; historicals tie to Zepto's actual reported revenue and net loss (FY23A-FY26A, per the DRHP).
B29: 3. Balance Sheet — fully linked; the Balance Check row (bottom) reads exactly 0 in every year, FY23A through FY33E.
B30: 4. Cash Flow — indirect method; includes a funding-plug mechanism so cash never goes negative, mirroring Zepto's actual reliance on successive private funding rounds.
B31: 5. DCF — unlevered FCF, WACC-discounted, Gordon Growth terminal value, plus a WACC x terminal-growth sensitivity grid.
B32: 6. Cell comments throughout flag which figures are actual disclosed numbers vs. modeled analyst estimates — hover over any cell with a red comment marker for its source.

Sheet Assumptions
A1: Zepto (Kiranakart Technologies Ltd) — Financial Model Assumptions
A2: Quick-commerce grocery delivery | Founded 2021 | IPO-bound (DRHP filed with SEBI, June 2026)
A4: (₹ Crore unless noted) | B4: FY23A | C4: FY24A | D4: FY25A | E4: FY26A | F4: FY27E | G4: FY28E | H4: FY29E | I4: FY30E | J4: FY31E | K4: FY32E | L4: FY33E
A6: A. REVENUE
A7: Revenue (₹ Cr) | B7: 2025 | C7: 4454 | D7: 11110 | E7: 22624 | F7: =E7*(1+F8) -> 35067.2 | G7: =F7*(1+G8) -> 49094.08 | H7: =G7*(1+H8) -> 63822.304 | I7: =H7*(1+I8) -> 79139.657 | J7: =I7*(1+J8) -> 94176.192 | K7: =J7*(1+K8) -> 108302.62 | L7: =K7*(1+L8) -> 121298.94
A8: Revenue growth % YoY | C8: =C7/B7-1 -> 1.1995062 | D8: =D7/C7-1 -> 1.4943871 | E8: =E7/D7-1 -> 1.0363636 | F8: 0.55 | G8: 0.4 | H8: 0.3 | I8: 0.24 | J8: 0.19 | K8: 0.15 | L8: 0.12
A10: B. COST STRUCTURE (as % of Revenue)
A11: COGS / Procurement of traded goods, % of revenue | B11: 0.82 | C11: 0.79 | D11: 0.755 | E11: 0.74 | F11: 0.725 | G11: 0.715 | H11: 0.705 | I11: 0.7 | J11: 0.695 | K11: 0.69 | L11: 0.685
A12: Delivery & handling, % of revenue | B12: 0.16 | C12: 0.15 | D12: 0.14 | E12: 0.1347 | F12: 0.13 | G12: 0.126 | H12: 0.122 | I12: 0.118 | J12: 0.114 | K12: 0.111 | L12: 0.108
A13: Employee benefits, % of revenue | B13: 0.12 | C13: 0.1 | D13: 0.085 | E13: 0.0789 | F13: 0.072 | G13: 0.066 | H13: 0.061 | I13: 0.057 | J13: 0.053 | K13: 0.05 | L13: 0.048
A14: Marketing & advertising, % of revenue | B14: 0.15 | C14: 0.12 | D14: 0.085 | E14: 0.065 | F14: 0.058 | G14: 0.052 | H14: 0.047 | I14: 0.043 | J14: 0.04 | K14: 0.038 | L14: 0.036
A15: Technology & cloud infrastructure, % of revenue | B15: 0.03 | C15: 0.025 | D15: 0.021 | E15: 0.019 | F15: 0.018 | G15: 0.017 | H15: 0.017 | I15: 0.016 | J15: 0.016 | K15: 0.015 | L15: 0.015
A16: G&A / other opex, % of revenue | B16: plug | C16: plug | D16: plug | E16: plug | F16: 0.075 | G16: 0.062 | H16: 0.052 | I16: 0.044 | J16: 0.038 | K16: 0.033 | L16: 0.029
A18: C. D&A, CAPEX, TAX & WORKING CAPITAL
A19: D&A, % of revenue | B19: 0.028 | C19: 0.026 | D19: 0.025 | E19: 0.024 | F19: 0.024 | G19: 0.024 | H19: 0.024 | I19: 0.024 | J19: 0.024 | K19: 0.024 | L19: 0.024
A20: Capex, % of revenue | B20: 0.06 | C20: 0.05 | D20: 0.045 | E20: 0.042 | F20: 0.04 | G20: 0.037 | H20: 0.034 | I20: 0.031 | J20: 0.029 | K20: 0.027 | L20: 0.026
A21: Corporate tax rate | B21: 0.2517 | C21: 0.2517 | D21: 0.2517 | E21: 0.2517 | F21: 0.2517 | G21: 0.2517 | H21: 0.2517 | I21: 0.2517 | J21: 0.2517 | K21: 0.2517 | L21: 0.2517
A22: Days Sales Outstanding (Receivables) | B22: 12 | C22: 13 | D22: 14 | E22: 15 | F22: 15 | G22: 15 | H22: 15 | I22: 15 | J22: 15 | K22: 15 | L22: 15
A23: Days Payable Outstanding | B23: 35 | C23: 38 | D23: 40 | E23: 42 | F23: 42 | G23: 42 | H23: 42 | I23: 42 | J23: 42 | K23: 42 | L23: 42
A24: Inventory Days (of COGS) | B24: 8 | C24: 9 | D24: 10 | E24: 10 | F24: 10 | G24: 10 | H24: 10 | I24: 10 | J24: 10 | K24: 10 | L24: 10
A25: Minimum operating cash balance (₹ Cr) | B25: 1000
A27: D. DISCOUNT RATE (WACC) & TERMINAL VALUE
A28: Risk-free rate (India 10Y G-Sec) | B28: 0.069
A29: Equity risk premium (India) | B29: 0.07
A30: Levered beta | B30: 1.3
A31: Cost of equity (CAPM) | B31: =B28+B30*B29 -> 0.16
A32: Pre-tax cost of debt | B32: 0.095
A33: After-tax cost of debt | B33: =B32*(1-B21) -> 0.0710885
A34: Target capital structure — % equity | B34: 0.9
A35: Target capital structure — % debt | B35: =1-B34 -> 0.1
A36: WACC | B36: =B34*B31+B35*B33 -> 0.15110885
A37: Terminal growth rate | B37: 0.05
A38: USD/INR exchange rate | B38: 87.5
A40: E. VALUATION BENCHMARKS (for comparison only — not model inputs)
A41: Last private funding round valuation | B41: 7
A42: IPO price band — implied valuation (low) | B42: 5.6
A43: IPO price band — implied valuation (high) | B43: 5.95

Sheet Income Statement
A1: Zepto — Income Statement
A2: ₹ Crore | FY23A-FY26A actual (DRHP), FY27E-FY33E projected
A4: (₹ Crore unless noted) | B4: FY23A | C4: FY24A | D4: FY25A | E4: FY26A | F4: FY27E | G4: FY28E | H4: FY29E | I4: FY30E | J4: FY31E | K4: FY32E | L4: FY33E
A6: Revenue | B6: =Assumptions!B7 -> 2025 | C6: =Assumptions!C7 -> 4454 | D6: =Assumptions!D7 -> 11110 | E6: =Assumptions!E7 -> 22624 | F6: =Assumptions!F7 -> 35067.2 | G6: =Assumptions!G7 -> 49094.08 | H6: =Assumptions!H7 -> 63822.304 | I6: =Assumptions!I7 -> 79139.657 | ... L6: =Assumptions!L7 -> 121298.94
A7: Revenue growth % YoY | C7: =C6/B6-1 -> 1.1995062 | D7: =D6/C6-1 -> 1.4943871 | E7: =E6/D6-1 -> 1.0363636 | F7: =F6/E6-1 -> 0.55 | G7: =G6/F6-1 -> 0.4 | H7: =H6/G6-1 -> 0.3 | I7: =I6/H6-1 -> 0.24 | J7: =J6/I6-1 -> 0.19 | ... L7: =L6/K6-1 -> 0.12
A9: COGS / Procurement of traded goods | B9: =-B6*Assumptions!B11 -> -1660.5 | C9: =-C6*Assumptions!C11 -> -3518.66 | D9: =-D6*Assumptions!D11 -> -8388.05 | E9: =-E6*Assumptions!E11 -> -16741.76 | F9: =-F6*Assumptions!F11 -> -25423.72 | G9: =-G6*Assumptions!G11 -> -35102.267 | H9: =-H6*Assumptions!H11 -> -44994.724 | I9: =-I6*Assumptions!I11 -> -55397.76 | ... L9: =-L6*Assumptions!L11 -> -83089.77
A10: Gross Profit | B10: =B6+B9 -> 364.5 | C10: =C6+C9 -> 935.34 | D10: =D6+D9 -> 2721.95 | E10: =E6+E9 -> 5882.24 | F10: =F6+F9 -> 9643.48 | G10: =G6+G9 -> 13991.813 | H10: =H6+H9 -> 18827.58 | I10: =I6+I9 -> 23741.897 | ... L10: =L6+L9 -> 38209.165
A11: Gross margin % | B11: =B10/B6 -> 0.18 | C11: =C10/C6 -> 0.21 | D11: =D10/D6 -> 0.245 | E11: =E10/E6 -> 0.26 | F11: =F10/F6 -> 0.275 | G11: =G10/G6 -> 0.285 | H11: =H10/H6 -> 0.295 | I11: =I10/I6 -> 0.3 | ... L11: =L10/L6 -> 0.315
A13: Operating Expenses
A14: Delivery & handling | B14: =-B6*Assumptions!B12 -> -324 | C14: =-C6*Assumptions!C12 -> -668.1 | D14: =-D6*Assumptions!D12 -> -1555.4 | E14: =-E6*Assumptions!E12 -> -3047.4528 | F14: =-F6*Assumptions!F12 -> -4558.736 | G14: =-G6*Assumptions!G12 -> -6185.8541 | H14: =-H6*Assumptions!H12 -> -7786.3211 | I14: =-I6*Assumptions!I12 -> -9338.4795 | ... L14: =-L6*Assumptions!L12 -> -13100.285
A15: Employee benefits expense | B15: =-B6*Assumptions!B13 -> -243 | C15: =-C6*Assumptions!C13 -> -445.4 | D15: =-D6*Assumptions!D13 -> -944.35 | E15: =-E6*Assumptions!E13 -> -1785.0336 | F15: =-F6*Assumptions!F13 -> -2524.8384 | G15: =-G6*Assumptions!G13 -> -3240.2093 | H15: =-H6*Assumptions!H13 -> -3893.1605 | I15: =-I6*Assumptions!I13 -> -4510.9604 | ... L15: =-L6*Assumptions!L13 -> -5822.3489
A16: Marketing & advertising | B16: =-B6*Assumptions!B14 -> -303.75 | C16: =-C6*Assumptions!C14 -> -534.48 | D16: =-D6*Assumptions!D14 -> -944.35 | E16: =-E6*Assumptions!E14 -> -1470.56 | F16: =-F6*Assumptions!F14 -> -2033.8976 | G16: =-G6*Assumptions!G14 -> -2552.8922 | H16: =-H6*Assumptions!H14 -> -2999.6483 | I16: =-I6*Assumptions!I14 -> -3403.0052 | ... L16: =-L6*Assumptions!L14 -> -4366.7617
A17: Technology & cloud infrastructure | B17: =-B6*Assumptions!B15 -> -60.75 | C17: =-C6*Assumptions!C15 -> -111.35 | D17: =-D6*Assumptions!D15 -> -233.31 | E17: =-E6*Assumptions!E15 -> -429.856 | F17: =-F6*Assumptions!F15 -> -631.2096 | G17: =-G6*Assumptions!G15 -> -834.59936 | H17: =-H6*Assumptions!H15 -> -1084.9792 | I17: =-I6*Assumptions!I15 -> -1266.2345 | ... L17: =-L6*Assumptions!L15 -> -1819.484
A18: G&A / other opex | B18: -648.3 | C18: -275.2 | D18: -3466.8 | E18: -4511.4 | F18: =-F6*Assumptions!F16 -> -2630.04 | G18: =-G6*Assumptions!G16 -> -3043.833 | H18: =-H6*Assumptions!H16 -> -3318.7598 | I18: =-I6*Assumptions!I16 -> -3482.1449 | J18: =-J6*Assumptions!J16 -> -3578.6953 | K18: =-K6*Assumptions!K16 -> -3573.9865 | L18: =-L6*Assumptions!L16 -> -3517.6691
A19: Total Operating Expenses | B19: =SUM(B14:B18) -> -1579.8 | C19: =SUM(C14:C18) -> -2034.53 | D19: =SUM(D14:D18) -> -7144.21 | E19: =SUM(E14:E18) -> -11244.302 | F19: =SUM(F14:F18) -> -12378.722 | G19: =SUM(G14:G18) -> -15857.388 | H19: =SUM(H14:H18) -> -19082.869 | I19: =SUM(I14:I18) -> -22000.825 | ... L19: =SUM(L14:L18) -> -28626.549
A20: EBITDA | B20: =B10+B19 -> -1215.3 | C20: =C10+C19 -> -1099.19 | D20: =D10+D19 -> -4422.26 | E20: =E10+E19 -> -5362.0624 | F20: =F10+F19 -> -2735.2416 | G20: =G10+G19 -> -1865.575 | H20: =H10+H19 -> -255.28922 | I20: =I10+I19 -> 1741.0725 | ... L20: =L10+L19 -> 9582.6159
A21: EBITDA margin % | B21: =B20/B6 -> -0.60014815 | C21: =C20/C6 -> -0.24678716 | D21: =D20/D6 -> -0.3980432 | E21: =E20/E6 -> -0.23700771 | F21: =F20/F6 -> -0.078 | G21: =G20/G6 -> -0.038 | H21: =H20/H6 -> -0.004 | I21: =I20/I6 -> 0.022 | ... L21: =L20/L6 -> 0.079
A22: D&A | B22: =-B6*Assumptions!B19 -> -56.7 | C22: =-C6*Assumptions!C19 -> -115.804 | D22: =-D6*Assumptions!D19 -> -277.75 | E22: =-E6*Assumptions!E19 -> -542.976 | F22: =-F6*Assumptions!F19 -> -841.6128 | G22: =-G6*Assumptions!G19 -> -1178.2579 | H22: =-H6*Assumptions!H19 -> -1531.7353 | I22: =-I6*Assumptions!I19 -> -1899.3518 | ... L22: =-L6*Assumptions!L19 -> -2911.1744
A23: EBIT | B23: =B20+B22 -> -1272 | C23: =C20+C22 -> -1214.994 | D23: =D20+D22 -> -4700.01 | E23: =E20+E22 -> -5905.0384 | F23: =F20+F22 -> -3576.8544 | G23: =G20+G22 -> -3043.833 | H23: =H20+H22 -> -1787.0245 | I23: =I20+I22 -> -158.27931 | ... L23: =L20+L22 -> 6671.4414
A24: Other income / (finance costs), net | B24: 0 | C24: 0 | D24: 0 | E24: 0 | F24: =0.5%*'Balance Sheet'!E7 -> 5 | G24: =0.5%*'Balance Sheet'!F7 -> 5 | H24: =0.5%*'Balance Sheet'!G7 -> 5 | I24: =0.5%*'Balance Sheet'!H7 -> 5 | J24: =0.5%*'Balance Sheet'!I7 -> 5 | K24: =0.5%*'Balance Sheet'!J7 -> 12.683364 | L24: =0.5%*'Balance Sheet'!K7 -> 29.627199
A25: Profit Before Tax | B25: =B23+B24 -> -1272 | C25: =C23+C24 -> -1214.994 | D25: =D23+D24 -> -4700.01 | E25: =E23+E24 -> -5905.0384 | F25: =F23+F24 -> -3571.8544 | G25: =G23+G24 -> -3038.833 | H25: =H23+H24 -> -1782.0245 | I25: =I23+I24 -> -153.27931 | ... L25: =L23+L24 -> 6701.0686
A26: Tax expense | B26: =-MAX(B25,0)*Assumptions!B21 -> 0 | C26: =-MAX(C25,0)*Assumptions!C21 -> 0 | D26: =-MAX(D25,0)*Assumptions!D21 -> 0 | E26: =-MAX(E25,0)*Assumptions!E21 -> 0 | F26: =-MAX(F25,0)*Assumptions!F21 -> 0 | G26: =-MAX(G25,0)*Assumptions!G21 -> 0 | H26: =-MAX(H25,0)*Assumptions!H21 -> 0 | I26: =-MAX(I25,0)*Assumptions!I21 -> 0 | ... L26: =-MAX(L25,0)*Assumptions!L21 -> -1686.659
A27: Net Income / (Loss) | B27: =B25+B26 -> -1272 | C27: =C25+C26 -> -1214.994 | D27: =D25+D26 -> -4700.01 | E27: =E25+E26 -> -5905.0384 | F27: =F25+F26 -> -3571.8544 | G27: =G25+G26 -> -3038.833 | H27: =H25+H26 -> -1782.0245 | I27: =I25+I26 -> -153.27931 | ... L27: =L25+L26 -> 5014.4097
A28: Net margin % | B28: =B27/B6 -> -0.62814815 | C28: =C27/C6 -> -0.27278716 | D28: =D27/D6 -> -0.4230432 | E28: =E27/E6 -> -0.26100771 | F28: =F27/F6 -> -0.10185742 | G28: =G27/G6 -> -0.061898155 | H28: =H27/H6 -> -0.027921657 | I28: =I27/I6 -> -0.0019368205 | ... L28: =L27/L6 -> 0.041339272

Sheet Balance Sheet
A1: Zepto — Balance Sheet
A2: ₹ Crore | FY23A-FY26A actual/estimated, FY27E-FY33E projected
A4: (₹ Crore unless noted) | B4: FY23A | C4: FY24A | D4: FY25A | E4: FY26A | F4: FY27E | G4: FY28E | H4: FY29E | I4: FY30E | J4: FY31E | K4: FY32E | L4: FY33E
A6: ASSETS
A7: Cash & cash equivalents | B7: ='Cash Flow'!B28 -> 1000 | C7: ='Cash Flow'!C28 -> 1000 | D7: ='Cash Flow'!D28 -> 1000 | E7: ='Cash Flow'!E28 -> 1000 | F7: ='Cash Flow'!F28 -> 1000 | G7: ='Cash Flow'!G28 -> 1000 | H7: ='Cash Flow'!H28 -> 1000 | I7: ='Cash Flow'!I28 -> 1000 | ... L7: ='Cash Flow'!L28 -> 11182.091
A8: Trade receivables | B8: ='Income Statement'!B6/365*Assumptions!B22 -> 66.575342 | C8: ='Income Statement'!C6/365*Assumptions!C22 -> 158.63562 | D8: ='Income Statement'!D6/365*Assumptions!D22 -> 426.13699 | E8: ='Income Statement'!E6/365*Assumptions!E22 -> 929.75342 | F8: ='Income Statement'!F6/365*Assumptions!F22 -> 1441.1178 | G8: ='Income Statement'!G6/365*Assumptions!G22 -> 2017.5649 | H8: ='Income Statement'!H6/365*Assumptions!H22 -> 2622.8344 | I8: ='Income Statement'!I6/365*Assumptions!I22 -> 3252.3147 | ... L8: ='Income Statement'!L6/365*Assumptions!L22 -> 4984.8877
A9: Inventory | B9: =-'Income Statement'!B9/365*Assumptions!B24 -> 36.394521 | C9: =-'Income Statement'!C9/365*Assumptions!C24 -> 86.761479 | D9: =-'Income Statement'!D9/365*Assumptions!D24 -> 229.80959 | E9: =-'Income Statement'!E9/365*Assumptions!E24 -> 458.67836 | F9: =-'Income Statement'!F9/365*Assumptions!F24 -> 696.54027 | G9: =-'Income Statement'!G9/365*Assumptions!G24 -> 961.70595 | H9: =-'Income Statement'!H9/365*Assumptions!H24 -> 1232.7322 | I9: =-'Income Statement'!I9/365*Assumptions!I24 -> 1517.7468 | ... L9: =-'Income Statement'!L9/365*Assumptions!L24 -> 2276.4321
A10: Other current assets | B10: =0.03*'Income Statement'!B6 -> 60.75 | C10: =0.03*'Income Statement'!C6 -> 133.62 | D10: =0.03*'Income Statement'!D6 -> 333.3 | E10: =0.03*'Income Statement'!E6 -> 678.72 | F10: =0.03*'Income Statement'!F6 -> 1052.016 | G10: =0.03*'Income Statement'!G6 -> 1472.8224 | H10: =0.03*'Income Statement'!H6 -> 1914.6691 | I10: =0.03*'Income Statement'!I6 -> 2374.1897 | ... L10: =0.03*'Income Statement'!L6 -> 3638.9681
A11: Total Current Assets | B11: =SUM(B7:B10) -> 1163.7199 | C11: =SUM(C7:C10) -> 1379.0171 | D11: =SUM(D7:D10) -> 1989.2466 | E11: =SUM(E7:E10) -> 3067.1518 | F11: =SUM(F7:F10) -> 4189.6741 | G11: =SUM(G7:G10) -> 5452.0933 | H11: =SUM(H7:H10) -> 6770.2357 | I11: =SUM(I7:I10) -> 8144.2512 | ... L11: =SUM(L7:L10) -> 22082.379
A13: Property, plant & equipment, net | B13: ='Income Statement'!B6*Assumptions!B20+'Income Statement'!B22 -> 64.8 | C13: =B13+'Income Statement'!C6*Assumptions!C20+'Income Statement'!C22 -> 171.696 | D13: =C13+'Income Statement'!D6*Assumptions!D20+'Income Statement'!D22 -> 393.896 | E13: =D13+'Income Statement'!E6*Assumptions!E20+'Income Statement'!E22 -> 801.128 | F13: =E13+'Income Statement'!F6*Assumptions!F20+'Income Statement'!F22 -> 1362.2032 | G13: =F13+'Income Statement'!G6*Assumptions!G20+'Income Statement'!G22 -> 2000.4262 | H13: =G13+'Income Statement'!H6*Assumptions!H20+'Income Statement'!H22 -> 2638.6493 | I13: =H13+'Income Statement'!I6*Assumptions!I20+'Income Statement'!I22 -> 3192.6269 | J13: =I13+'Income Statement'!J6*Assumptions!J20+'Income Statement'!J22 -> 3663.5078 | ... L13: =K13+'Income Statement'!L6*Assumptions!L20+'Income Statement'!L22 -> 4231.0136
A14: Other non-current assets (incl. intangibles) | B14: =0.018*'Income Statement'!B6 -> 36.45 | C14: =0.018*'Income Statement'!C6 -> 80.172 | D14: =0.018*'Income Statement'!D6 -> 199.98 | E14: =0.018*'Income Statement'!E6 -> 407.232 | F14: =0.018*'Income Statement'!F6 -> 631.2096 | G14: =0.018*'Income Statement'!G6 -> 883.69344 | H14: =0.018*'Income Statement'!H6 -> 1148.8015 | I14: =0.018*'Income Statement'!I6 -> 1424.5138 | ... L14: =0.018*'Income Statement'!L6 -> 2183.3808
A15: Total Non-Current Assets | B15: =SUM(B13:B14) -> 101.25 | C15: =SUM(C13:C14) -> 251.868 | D15: =SUM(D13:D14) -> 593.876 | E15: =SUM(E13:E14) -> 1208.36 | F15: =SUM(F13:F14) -> 1993.4128 | G15: =SUM(G13:G14) -> 2884.1197 | H15: =SUM(H13:H14) -> 3787.4508 | I15: =SUM(I13:I14) -> 4617.1407 | ... L15: =SUM(L13:L14) -> 6414.3944
A16: TOTAL ASSETS | B16: =B11+B15 -> 1264.9699 | C16: =C11+C15 -> 1630.8851 | D16: =D11+D15 -> 2583.1226 | E16: =E11+E15 -> 4275.5118 | F16: =F11+F15 -> 6183.0869 | G16: =G11+G15 -> 8336.213 | H16: =H11+H15 -> 10557.686 | I16: =I11+I15 -> 12761.392 | ... L16: =L11+L15 -> 28496.774
A18: LIABILITIES
A19: Trade payables | B19: =-'Income Statement'!B9/365*Assumptions!B23 -> 159.22603 | C19: =-'Income Statement'!C9/365*Assumptions!C23 -> 366.32625 | D19: =-'Income Statement'!D9/365*Assumptions!D23 -> 919.23836 | E19: =-'Income Statement'!E9/365*Assumptions!E23 -> 1926.4491 | F19: =-'Income Statement'!F9/365*Assumptions!F23 -> 2925.4692 | G19: =-'Income Statement'!G9/365*Assumptions!G23 -> 4039.165 | H19: =-'Income Statement'!H9/365*Assumptions!H23 -> 5177.4751 | I19: =-'Income Statement'!I9/365*Assumptions!I23 -> 6374.5368 | ... L19: =-'Income Statement'!L9/365*Assumptions!L23 -> 9561.0147
A20: Other current liabilities & provisions | B20: =0.07*'Income Statement'!B6 -> 141.75 | C20: =0.07*'Income Statement'!C6 -> 311.78 | D20: =0.07*'Income Statement'!D6 -> 777.7 | E20: =0.07*'Income Statement'!E6 -> 1583.68 | F20: =0.07*'Income Statement'!F6 -> 2454.704 | G20: =0.07*'Income Statement'!G6 -> 3436.5856 | H20: =0.07*'Income Statement'!H6 -> 4467.5613 | I20: =0.07*'Income Statement'!I6 -> 5539.776 | ... L20: =0.07*'Income Statement'!L6 -> 8490.9255
A21: Total Current Liabilities | B21: =SUM(B19:B20) -> 300.97603 | C21: =SUM(C19:C20) -> 678.10625 | D21: =SUM(D19:D20) -> 1696.9384 | E21: =SUM(E19:E20) -> 3510.1291 | F21: =SUM(F19:F20) -> 5380.1732 | G21: =SUM(G19:G20) -> 7475.7506 | H21: =SUM(H19:H20) -> 9645.0364 | I21: =SUM(I19:I20) -> 11914.313 | ... L21: =SUM(L19:L20) -> 18051.94
A22: Borrowings (long-term) | B22: 0 | C22: 0 | D22: 0 | E22: 0 | F22: 0 | G22: 0 | H22: 0 | I22: 0 | J22: 0 | K22: 0 | L22: 0
A23: TOTAL LIABILITIES | B23: =B21+B22 -> 300.97603 | C23: =C21+C22 -> 678.10625 | D23: =D21+D22 -> 1696.9384 | E23: =E21+E22 -> 3510.1291 | F23: =F21+F22 -> 5380.1732 | G23: =G21+G22 -> 7475.7506 | H23: =H21+H22 -> 9645.0364 | I23: =I21+I22 -> 11914.313 | ... L23: =L21+L22 -> 18051.94
A25: EQUITY
A26: Share capital & securities premium | B26: ='Cash Flow'!B22+'Cash Flow'!B23 -> 2235.9938 | C26: =B26+'Cash Flow'!C23 -> 3439.7728 | D26: =C26+'Cash Flow'!D23 -> 8073.1882 | E26: =D26+'Cash Flow'!E23 -> 13857.425 | F26: =E26+'Cash Flow'!F23 -> 17466.811 | G26: =F26+'Cash Flow'!G23 -> 20563.192 | H26: =G26+'Cash Flow'!H23 -> 22397.404 | I26: =H26+'Cash Flow'!I23 -> 22485.113 | J26: =I26+'Cash Flow'!J23 -> 22485.113 | ... L26: =K26+'Cash Flow'!L23 -> 22485.113
A27: Retained earnings / (accumulated deficit) | B27: ='Income Statement'!B27 -> -1272 | C27: =B27+'Income Statement'!C27 -> -2486.994 | D27: =C27+'Income Statement'!D27 -> -7187.004 | E27: =D27+'Income Statement'!E27 -> -13092.042 | F27: =E27+'Income Statement'!F27 -> -16663.897 | G27: =F27+'Income Statement'!G27 -> -19702.73 | H27: =G27+'Income Statement'!H27 -> -21484.754 | I27: =H27+'Income Statement'!I27 -> -21638.034 | J27: =I27+'Income Statement'!J27 -> -20224.851 | ... L27: =K27+'Income Statement'!L27 -> -12040.279
A28: Total Equity | B28: =B26+B27 -> 963.99384 | C28: =C26+C27 -> 952.77885 | D28: =D26+D27 -> 886.18422 | E28: =E26+E27 -> 765.38268 | F28: =F26+F27 -> 802.91373 | G28: =G26+G27 -> 860.46237 | H28: =H26+H27 -> 912.65005 | I28: =I26+I27 -> 847.07919 | ... L28: =L26+L27 -> 10444.833
A29: TOTAL LIABILITIES & EQUITY | B29: =B23+B28 -> 1264.9699 | C29: =C23+C28 -> 1630.8851 | D29: =D23+D28 -> 2583.1226 | E29: =E23+E28 -> 4275.5118 | F29: =F23+F28 -> 6183.0869 | G29: =G23+G28 -> 8336.213 | H29: =H23+H28 -> 10557.686 | I29: =I23+I28 -> 12761.392 | ... L29: =L23+L28 -> 28496.774
A31: Balance Check (Assets - Liabilities & Equity) | B31: =B16-B29 -> 0 | C31: =C16-C29 -> 0 | D31: =D16-D29 -> 0 | E31: =E16-E29 -> 0 | F31: =F16-F29 -> 0 | G31: =G16-G29 -> 0 | H31: =H16-H29 -> 0 | I31: =I16-I29 -> 0 | ... L31: =L16-L29 -> 0

Sheet Cash Flow
A1: Zepto — Cash Flow Statement
A2: ₹ Crore | FY23A-FY26A modeled from actuals, FY27E-FY33E projected
A4: (₹ Crore unless noted) | B4: FY23A | C4: FY24A | D4: FY25A | E4: FY26A | F4: FY27E | G4: FY28E | H4: FY29E | I4: FY30E | J4: FY31E | K4: FY32E | L4: FY33E
A6: Cash Flow from Operations
A7: Net Income / (Loss) | B7: ='Income Statement'!B27 -> -1272 | C7: ='Income Statement'!C27 -> -1214.994 | D7: ='Income Statement'!D27 -> -4700.01 | E7: ='Income Statement'!E27 -> -5905.0384 | F7: ='Income Statement'!F27 -> -3571.8544 | G7: ='Income Statement'!G27 -> -3038.833 | H7: ='Income Statement'!H27 -> -1782.0245 | I7: ='Income Statement'!I27 -> -153.27931 | ... L7: ='Income Statement'!L27 -> 5014.4097
A8: (+) D&A | B8: =-'Income Statement'!B22 -> 56.7 | C8: =-'Income Statement'!C22 -> 115.804 | D8: =-'Income Statement'!D22 -> 277.75 | E8: =-'Income Statement'!E22 -> 542.976 | F8: =-'Income Statement'!F22 -> 841.6128 | G8: =-'Income Statement'!G22 -> 1178.2579 | H8: =-'Income Statement'!H22 -> 1531.7353 | I8: =-'Income Statement'!I22 -> 1899.3518 | ... L8: =-'Income Statement'!L22 -> 2911.1744
A9: (Increase) / decrease in receivables | B9: =-'Balance Sheet'!B8 -> -66.575342 | C9: =-('Balance Sheet'!C8-'Balance Sheet'!B8) -> -92.060274 | D9: =-('Balance Sheet'!D8-'Balance Sheet'!C8) -> -267.50137 | E9: =-('Balance Sheet'!E8-'Balance Sheet'!D8) -> -503.61644 | F9: =-('Balance Sheet'!F8-'Balance Sheet'!E8) -> -511.36438 | G9: =-('Balance Sheet'!G8-'Balance Sheet'!F8) -> -576.44712 | H9: =-('Balance Sheet'!H8-'Balance Sheet'!G8) -> -605.26948 | I9: =-('Balance Sheet'!I8-'Balance Sheet'!H8) -> -629.48026 | J9: =-('Balance Sheet'!J8-'Balance Sheet'!I8) -> -617.93979 | ... L9: =-('Balance Sheet'!L8-'Balance Sheet'!K8) -> -534.09512
A10: (Increase) / decrease in inventory | B10: =-'Balance Sheet'!B9 -> -36.394521 | C10: =-('Balance Sheet'!C9-'Balance Sheet'!B9) -> -50.366959 | D10: =-('Balance Sheet'!D9-'Balance Sheet'!C9) -> -143.04811 | E10: =-('Balance Sheet'!E9-'Balance Sheet'!D9) -> -228.86877 | F10: =-('Balance Sheet'!F9-'Balance Sheet'!E9) -> -237.86192 | G10: =-('Balance Sheet'!G9-'Balance Sheet'!F9) -> -265.16568 | H10: =-('Balance Sheet'!H9-'Balance Sheet'!G9) -> -271.02622 | I10: =-('Balance Sheet'!I9-'Balance Sheet'!H9) -> -285.01467 | J10: =-('Balance Sheet'!J9-'Balance Sheet'!I9) -> -275.47105 | ... L10: =-('Balance Sheet'!L9-'Balance Sheet'!K9) -> -229.06746
A11: (Increase) / decrease in other current assets | B11: =-'Balance Sheet'!B10 -> -60.75 | C11: =-('Balance Sheet'!C10-'Balance Sheet'!B10) -> -72.87 | D11: =-('Balance Sheet'!D10-'Balance Sheet'!C10) -> -199.68 | E11: =-('Balance Sheet'!E10-'Balance Sheet'!D10) -> -345.42 | F11: =-('Balance Sheet'!F10-'Balance Sheet'!E10) -> -373.296 | G11: =-('Balance Sheet'!G10-'Balance Sheet'!F10) -> -420.8064 | H11: =-('Balance Sheet'!H10-'Balance Sheet'!G10) -> -441.84672 | I11: =-('Balance Sheet'!I10-'Balance Sheet'!H10) -> -459.52059 | J11: =-('Balance Sheet'!J10-'Balance Sheet'!I10) -> -451.09604 | ... L11: =-('Balance Sheet'!L10-'Balance Sheet'!K10) -> -389.88943
A12: Increase / (decrease) in payables | B12: ='Balance Sheet'!B19 -> 159.22603 | C12: =('Balance Sheet'!C19-'Balance Sheet'!B19) -> 207.10022 | D12: =('Balance Sheet'!D19-'Balance Sheet'!C19) -> 552.91211 | E12: =('Balance Sheet'!E19-'Balance Sheet'!D19) -> 1007.2107 | F12: =('Balance Sheet'!F19-'Balance Sheet'!E19) -> 999.02005 | G12: =('Balance Sheet'!G19-'Balance Sheet'!F19) -> 1113.6958 | H12: =('Balance Sheet'!H19-'Balance Sheet'!G19) -> 1138.3101 | I12: =('Balance Sheet'!I19-'Balance Sheet'!H19) -> 1197.0616 | J12: =('Balance Sheet'!J19-'Balance Sheet'!I19) -> 1156.9784 | ... L12: =('Balance Sheet'!L19-'Balance Sheet'!K19) -> 962.08333
A13: Increase / (decrease) in other current liabilities | B13: ='Balance Sheet'!B20 -> 141.75 | C13: =('Balance Sheet'!C20-'Balance Sheet'!B20) -> 170.03 | D13: =('Balance Sheet'!D20-'Balance Sheet'!C20) -> 465.92 | E13: =('Balance Sheet'!E20-'Balance Sheet'!D20) -> 805.98 | F13: =('Balance Sheet'!F20-'Balance Sheet'!E20) -> 871.024 | G13: =('Balance Sheet'!G20-'Balance Sheet'!F20) -> 981.8816 | H13: =('Balance Sheet'!H20-'Balance Sheet'!G20) -> 1030.9757 | I13: =('Balance Sheet'!I20-'Balance Sheet'!H20) -> 1072.2147 | J13: =('Balance Sheet'!J20-'Balance Sheet'!I20) -> 1052.5574 | ... L13: =('Balance Sheet'!L20-'Balance Sheet'!K20) -> 909.74201
A14: Cash Flow from Operations | B14: =SUM(B7:B13) -> -1078.0438 | C14: =SUM(C7:C13) -> -937.35701 | D14: =SUM(D7:D13) -> -4013.6574 | E14: =SUM(E7:E13) -> -4626.7769 | F14: =SUM(F7:F13) -> -1982.7198 | G14: =SUM(G7:G13) -> -1027.4168 | H14: =SUM(H7:H13) -> 600.85418 | I14: =SUM(I7:I13) -> 2641.3333 | ... L14: =SUM(L7:L13) -> 8644.3574
A16: Cash Flow from Investing
A17: Capital expenditure | B17: =-'Income Statement'!B6*Assumptions!B20 -> -121.5 | C17: =-'Income Statement'!C6*Assumptions!C20 -> -222.7 | D17: =-'Income Statement'!D6*Assumptions!D20 -> -499.95 | E17: =-'Income Statement'!E6*Assumptions!E20 -> -950.208 | F17: =-'Income Statement'!F6*Assumptions!F20 -> -1402.688 | G17: =-'Income Statement'!G6*Assumptions!G20 -> -1816.481 | H17: =-'Income Statement'!H6*Assumptions!H20 -> -2169.9583 | I17: =-'Income Statement'!I6*Assumptions!I20 -> -2453.3294 | ... L17: =-'Income Statement'!L6*Assumptions!L20 -> -3153.7723
A18: (Increase) / decrease in other non-current assets | B18: =-'Balance Sheet'!B14 -> -36.45 | C18: =-('Balance Sheet'!C14-'Balance Sheet'!B14) -> -43.722 | D18: =-('Balance Sheet'!D14-'Balance Sheet'!C14) -> -119.808 | E18: =-('Balance Sheet'!E14-'Balance Sheet'!D14) -> -207.252 | F18: =-('Balance Sheet'!F14-'Balance Sheet'!E14) -> -223.9776 | G18: =-('Balance Sheet'!G14-'Balance Sheet'!F14) -> -252.48384 | H18: =-('Balance Sheet'!H14-'Balance Sheet'!G14) -> -265.10803 | I18: =-('Balance Sheet'!I14-'Balance Sheet'!H14) -> -275.71235 | J18: =-('Balance Sheet'!J14-'Balance Sheet'!I14) -> -270.65763 | ... L18: =-('Balance Sheet'!L14-'Balance Sheet'!K14) -> -233.93366
A19: Cash Flow from Investing | B19: =B17+B18 -> -157.95 | C19: =C17+C18 -> -266.422 | D19: =D17+D18 -> -619.758 | E19: =E17+E18 -> -1157.46 | F19: =F17+F18 -> -1626.6656 | G19: =G17+G18 -> -2068.9648 | H19: =H17+H18 -> -2435.0664 | I19: =I17+I18 -> -2729.0417 | ... L19: =L17+L18 -> -3387.706
A21: Cash Flow from Financing
A22: Beginning cash balance | B22: 350 | C22: =B28 -> 1000 | D22: =C28 -> 1000 | E22: =D28 -> 1000 | F22: =E28 -> 1000 | G22: =F28 -> 1000 | H22: =G28 -> 1000 | I22: =H28 -> 1000 | J22: =I28 -> 1000 | ... L22: =K28 -> 5925.4398
A23: External equity funding raised (plug) | B23: =MAX(0, Assumptions!$B$25 - (B22+B14+B19)) -> 1885.9938 | C23: =MAX(0, Assumptions!$B$25 - (C22+C14+C19)) -> 1203.779 | D23: =MAX(0, Assumptions!$B$25 - (D22+D14+D19)) -> 4633.4154 | E23: =MAX(0, Assumptions!$B$25 - (E22+E14+E19)) -> 5784.2369 | F23: =MAX(0, Assumptions!$B$25 - (F22+F14+F19)) -> 3609.3854 | G23: =MAX(0, Assumptions!$B$25 - (G22+G14+G19)) -> 3096.3816 | H23: =MAX(0, Assumptions!$B$25 - (H22+H14+H19)) -> 1834.2122 | I23: =MAX(0, Assumptions!$B$25 - (I22+I14+I19)) -> 87.708454 | ... L23: =MAX(0, Assumptions!$B$25 - (L22+L14+L19)) -> 0
A24: Debt raised / (repaid) | B24: 0 | C24: 0 | D24: 0 | E24: 0 | F24: 0 | G24: 0 | H24: 0 | I24: 0 | J24: 0 | K24: 0 | L24: 0
A25: Cash Flow from Financing | B25: =B23+B24 -> 1885.9938 | C25: =C23+C24 -> 1203.779 | D25: =D23+D24 -> 4633.4154 | E25: =E23+E24 -> 5784.2369 | F25: =F23+F24 -> 3609.3854 | G25: =G23+G24 -> 3096.3816 | H25: =H23+H24 -> 1834.2122 | I25: =I23+I24 -> 87.708454 | ... L25: =L23+L24 -> 0
A27: Net change in cash | B27: =B14+B19+B25 -> 650 | C27: =C14+C19+C25 -> 0 | D27: =D14+D19+D25 -> 0 | E27: =E14+E19+E25 -> 0 | F27: =F14+F19+F25 -> 0 | G27: =G14+G19+G25 -> 0 | H27: =H14+H19+H25 -> 0 | I27: =I14+I19+I25 -> 0 | ... L27: =L14+L19+L25 -> 5256.6515
A28: Ending cash balance | B28: =B22+B27 -> 1000 | C28: =C22+C27 -> 1000 | D28: =D22+D27 -> 1000 | E28: =E22+E27 -> 1000 | F28: =F22+F27 -> 1000 | G28: =G22+G27 -> 1000 | H28: =H22+H27 -> 1000 | I28: =I22+I27 -> 1000 | ... L28: =L22+L27 -> 11182.091

Sheet DCF
A1: Zepto — Discounted Cash Flow Valuation
A2: ₹ Crore unless noted | Explicit forecast: FY27E-FY33E
A4: (₹ Crore unless noted) | B4: FY23A | C4: FY24A | D4: FY25A | E4: FY26A | F4: FY27E | G4: FY28E | H4: FY29E | I4: FY30E | J4: FY31E | K4: FY32E | L4: FY33E
A6: Unlevered Free Cash Flow Build
A7: EBIT | F7: ='Income Statement'!F23 -> -3576.8544 | G7: ='Income Statement'!G23 -> -3043.833 | H7: ='Income Statement'!H23 -> -1787.0245 | I7: ='Income Statement'!I23 -> -158.27931 | J7: ='Income Statement'!J23 -> 1883.5238 | K7: ='Income Statement'!K23 -> 4223.8022 | L7: ='Income Statement'!L23 -> 6671.4414
A8: Less: Tax on EBIT (unlevered, at marginal rate) | F8: =-MAX(F7,0)*Assumptions!F21 -> 0 | G8: =-MAX(G7,0)*Assumptions!G21 -> 0 | H8: =-MAX(H7,0)*Assumptions!H21 -> 0 | I8: =-MAX(I7,0)*Assumptions!I21 -> 0 | J8: =-MAX(J7,0)*Assumptions!J21 -> -474.08295 | K8: =-MAX(K7,0)*Assumptions!K21 -> -1063.131 | L8: =-MAX(L7,0)*Assumptions!L21 -> -1679.2018
A9: NOPAT | F9: =F7+F8 -> -3576.8544 | G9: =G7+G8 -> -3043.833 | H9: =H7+H8 -> -1787.0245 | I9: =I7+I8 -> -158.27931 | J9: =J7+J8 -> 1409.4409 | K9: =K7+K8 -> 3160.6712 | L9: =L7+L8 -> 4992.2396
A10: (+) D&A | F10: =-'Income Statement'!F22 -> 841.6128 | G10: =-'Income Statement'!G22 -> 1178.2579 | H10: =-'Income Statement'!H22 -> 1531.7353 | I10: =-'Income Statement'!I22 -> 1899.3518 | J10: =-'Income Statement'!J22 -> 2260.2286 | K10: =-'Income Statement'!K22 -> 2599.2629 | L10: =-'Income Statement'!L22 -> 2911.1744
A11: (–) Capital expenditure | F11: ='Cash Flow'!F17 -> -1402.688 | G11: ='Cash Flow'!G17 -> -1816.481 | H11: ='Cash Flow'!H17 -> -2169.9583 | I11: ='Cash Flow'!I17 -> -2453.3294 | J11: ='Cash Flow'!J17 -> -2731.1096 | K11: ='Cash Flow'!K17 -> -2924.1708 | L11: ='Cash Flow'!L17 -> -3153.7723
A12: (–) Increase in net working capital | F12: ='Cash Flow'!F9+'Cash Flow'!F10+'Cash Flow'!F11+'Cash Flow'!F12+'Cash Flow'!F13 -> 747.52175 | G12: ='Cash Flow'!G9+'Cash Flow'!G10+'Cash Flow'!G11+'Cash Flow'!G12+'Cash Flow'!G13 -> 833.15824 | H12: ='Cash Flow'!H9+'Cash Flow'!H10+'Cash Flow'!H11+'Cash Flow'!H12+'Cash Flow'!H13 -> 851.14339 | I12: ='Cash Flow'!I9+'Cash Flow'!I10+'Cash Flow'!I11+'Cash Flow'!I12+'Cash Flow'!I13 -> 895.26081 | J12: ='Cash Flow'!J9+'Cash Flow'!J10+'Cash Flow'!J11+'Cash Flow'!J12+'Cash Flow'!J13 -> 865.02897 | K12: ='Cash Flow'!K9+'Cash Flow'!K10+'Cash Flow'!K11+'Cash Flow'!K12+'Cash Flow'!K13 -> 797.78845 | L12: ='Cash Flow'!L9+'Cash Flow'!L10+'Cash Flow'!L11+'Cash Flow'!L12+'Cash Flow'!L13 -> 718.77334
A13: Unlevered Free Cash Flow | F13: =F9+F10+F11+F12 -> -3390.4078 | G13: =G9+G10+G11+G12 -> -2848.8978 | H13: =H9+H10+H11+H12 -> -1574.1042 | I13: =I9+I10+I11+I12 -> 183.0039 | J13: =J9+J10+J11+J12 -> 1803.5889 | K13: =K9+K10+K11+K12 -> 3633.5518 | L13: =L9+L10+L11+L12 -> 5468.4151
A15: Discounting
A16: Discount period (years, end-of-year convention) | F16: 1 | G16: 2 | H16: 3 | I16: 4 | J16: 5 | K16: 6 | L16: 7
A17: Discount factor | F17: =1/(1+Assumptions!$B$36)^F16 -> 0.86872758 | G17: =1/(1+Assumptions!$B$36)^G16 -> 0.7546876 | H17: =1/(1+Assumptions!$B$36)^H16 -> 0.65561793 | I17: =1/(1+Assumptions!$B$36)^I16 -> 0.56955337 | J17: =1/(1+Assumptions!$B$36)^J16 -> 0.49478672 | K17: =1/(1+Assumptions!$B$36)^K16 -> 0.42983487 | L17: =1/(1+Assumptions!$B$36)^L16 -> 0.3734094
A18: PV of Unlevered FCF | F18: =F13*F17 -> -2945.3408 | G18: =G13*G17 -> -2150.0278 | H18: =H13*H17 -> -1032.0109 | I18: =I13*I17 -> 104.23049 | J18: =J13*J17 -> 892.39184 | K18: =K13*K17 -> 1561.8272 | L18: =L13*L17 -> 2041.9576
A20: Enterprise & Equity Value
A21: Sum of PV of explicit-period FCF (FY27E-FY33E) | B21: =SUM(F18:L18) -> -1526.9723
A22: Terminal value (Gordon Growth, at end of FY33E) | B22: =L13*(1+Assumptions!$B$37)/(Assumptions!$B$36-Assumptions!$B$37) -> 56788.657
A23: PV of terminal value | B23: =B22*L17 -> 21205.419
A24: Terminal value as % of Enterprise Value | B24: =B23/B25 -> 1.0775962
A25: Enterprise Value | B25: =B21+B23 -> 19678.446
A26: Less: Net debt (Total debt – cash), as of FY26A | B26: ='Balance Sheet'!E22-'Balance Sheet'!E7 -> -1000
A27: Equity Value (₹ Cr) | B27: =B25-B26 -> 20678.446
A28: Equity Value (US$ billion) | B28: =B27/Assumptions!$B$38/100 -> 2.363251
A30: Valuation Benchmarking (context, not model inputs)
A31: Implied premium / (discount) vs. last private round ($7.0bn, Oct-2025) | B31: =B28/Assumptions!$B$41-1 -> -0.66239271
A32: Implied premium / (discount) vs. IPO band midpoint (~$5.78bn) | B32: =B28/((Assumptions!$B$42+Assumptions!$B$43)/2)-1 -> -0.59077905
A34: Sensitivity: Equity Value (US$ bn) by WACC and Terminal Growth Rate
A35: WACC \ Terminal growth → | C35: 0.03 | D35: 0.04 | E35: 0.05 | F35: 0.06 | G35: 0.07
B36: 0.12 | C36: =(SUMPRODUCT($F$13:$L$13,1/(1+$B36)^($F$16:$L$16))+$L$13*(1+C$35)/($B36-C$35)/(1+$B36)^$L$16-B26)/Assumptions!$B$38/100 -> 3.2394148 | D36: =(SUMPRODUCT($F$13:$L$13,1/(1+$B36)^($F$16:$L$16))+$L$13*(1+D$35)/($B36-D$35)/(1+$B36)^$L$16-B26)/Assumptions!$B$38/100 -> 3.6791718 | E36: =(SUMPRODUCT($F$13:$L$13,1/(1+$B36)^($F$16:$L$16))+$L$13*(1+E$35)/($B36-E$35)/(1+$B36)^$L$16-B26)/Assumptions!$B$38/100 -> 4.2445737 | F36: =(SUMPRODUCT($F$13:$L$13,1/(1+$B36)^($F$16:$L$16))+$L$13*(1+F$35)/($B36-F$35)/(1+$B36)^$L$16-B26)/Assumptions!$B$38/100 -> 4.9984429 | G36: =(SUMPRODUCT($F$13:$L$13,1/(1+$B36)^($F$16:$L$16))+$L$13*(1+G$35)/($B36-G$35)/(1+$B36)^$L$16-B26)/Assumptions!$B$38/100 -> 6.0538598
B37: 0.135 | C37: =(SUMPRODUCT($F$13:$L$13,1/(1+$B37)^($F$16:$L$16))+$L$13*(1+C$35)/($B37-C$35)/(1+$B37)^$L$16-B26)/Assumptions!$B$38/100 -> 2.4975255 | D37: =(SUMPRODUCT($F$13:$L$13,1/(1+$B37)^($F$16:$L$16))+$L$13*(1+D$35)/($B37-D$35)/(1+$B37)^$L$16-B26)/Assumptions!$B$38/100 -> 2.7905914 | E37: =(SUMPRODUCT($F$13:$L$13,1/(1+$B37)^($F$16:$L$16))+$L$13*(1+E$35)/($B37-E$35)/(1+$B37)^$L$16-B26)/Assumptions!$B$38/100 -> 3.152614 | F37: =(SUMPRODUCT($F$13:$L$13,1/(1+$B37)^($F$16:$L$16))+$L$13*(1+F$35)/($B37-F$35)/(1+$B37)^$L$16-B26)/Assumptions!$B$38/100 -> 3.611176 | G37: =(SUMPRODUCT($F$13:$L$13,1/(1+$B37)^($F$16:$L$16))+$L$13*(1+G$35)/($B37-G$35)/(1+$B37)^$L$16-B26)/Assumptions!$B$38/100 -> 4.210834
B38: 0.1511 | C38: =(SUMPRODUCT($F$13:$L$13,1/(1+$B38)^($F$16:$L$16))+$L$13*(1+C$35)/($B38-C$35)/(1+$B38)^$L$16-B26)/Assumptions!$B$38/100 -> 1.924766 | D38: =(SUMPRODUCT($F$13:$L$13,1/(1+$B38)^($F$16:$L$16))+$L$13*(1+D$35)/($B38-D$35)/(1+$B38)^$L$16-B26)/Assumptions!$B$38/100 -> 2.1244378 | E38: =(SUMPRODUCT($F$13:$L$13,1/(1+$B38)^($F$16:$L$16))+$L$13*(1+E$35)/($B38-E$35)/(1+$B38)^$L$16-B26)/Assumptions!$B$38/100 -> 2.3636096 | F38: =(SUMPRODUCT($F$13:$L$13,1/(1+$B38)^($F$16:$L$16))+$L$13*(1+F$35)/($B38-F$35)/(1+$B38)^$L$16-B26)/Assumptions!$B$38/100 -> 2.6552889 | G38: =(SUMPRODUCT($F$13:$L$13,1/(1+$B38)^($F$16:$L$16))+$L$13*(1+G$35)/($B38-G$35)/(1+$B38)^$L$16-B26)/Assumptions!$B$38/100 -> 3.0188989
B39: 0.165 | C39: =(SUMPRODUCT($F$13:$L$13,1/(1+$B39)^($F$16:$L$16))+$L$13*(1+C$35)/($B39-C$35)/(1+$B39)^$L$16-B26)/Assumptions!$B$38/100 -> 1.5531971 | D39: =(SUMPRODUCT($F$13:$L$13,1/(1+$B39)^($F$16:$L$16))+$L$13*(1+D$35)/($B39-D$35)/(1+$B39)^$L$16-B26)/Assumptions!$B$38/100 -> 1.7013309 | E39: =(SUMPRODUCT($F$13:$L$13,1/(1+$B39)^($F$16:$L$16))+$L$13*(1+E$35)/($B39-E$35)/(1+$B39)^$L$16-B26)/Assumptions!$B$38/100 -> 1.8752271 | F39: =(SUMPRODUCT($F$13:$L$13,1/(1+$B39)^($F$16:$L$16))+$L$13*(1+F$35)/($B39-F$35)/(1+$B39)^$L$16-B26)/Assumptions!$B$38/100 -> 2.0822463 | G39: =(SUMPRODUCT($F$13:$L$13,1/(1+$B39)^($F$16:$L$16))+$L$13*(1+G$35)/($B39-G$35)/(1+$B39)^$L$16-B26)/Assumptions!$B$38/100 -> 2.3328486
B40: 0.18 | C40: =(SUMPRODUCT($F$13:$L$13,1/(1+$B40)^($F$16:$L$16))+$L$13*(1+C$35)/($B40-C$35)/(1+$B40)^$L$16-B26)/Assumptions!$B$38/100 -> 1.2406765 | D40: =(SUMPRODUCT($F$13:$L$13,1/(1+$B40)^($F$16:$L$16))+$L$13*(1+D$35)/($B40-D$35)/(1+$B40)^$L$16-B26)/Assumptions!$B$38/100 -> 1.3509172 | E40: =(SUMPRODUCT($F$13:$L$13,1/(1+$B40)^($F$16:$L$16))+$L$13*(1+E$35)/($B40-E$35)/(1+$B40)^$L$16-B26)/Assumptions!$B$38/100 -> 1.478118 | F40: =(SUMPRODUCT($F$13:$L$13,1/(1+$B40)^($F$16:$L$16))+$L$13*(1+F$35)/($B40-F$35)/(1+$B40)^$L$16-B26)/Assumptions!$B$38/100 -> 1.626519 | G40: =(SUMPRODUCT($F$13:$L$13,1/(1+$B40)^($F$16:$L$16))+$L$13*(1+G$35)/($B40-G$35)/(1+$B40)^$L$16-B26)/Assumptions!$B$38/100 -> 1.801902
A42: Base case highlighted; other cells recalculate live off the formulas above.
